{"id": "gigya", "name": "Gigya", "category": "site_analytics", "website_url": null, "ghostery_id": "2746", "company_id": "gigya", "iab_vendor": null, "truste_type": "Retargeting / Optimization", "description": "Gigya is Software as a Service (SaaS) technology that makes websites social, integrating online businesses with the top social networks and identity providers including Facebook, Twitter and LinkedIn. ", "privacy_url": "http://www.gigya.com/privacy-policy/", "domains": ["gigya.com"], "overview": {"bad_qs": 0.007834901968270937, "beacon": 0.0, "content_length": 82534.53221397071, "cookies": 0.6142723506614994, "font": 0.0, "has_blocking": 0.4907905538267692, "hosts": 1.0, "https": 1.5086439739600237, "iframe": 0.6960875126477157, "image": 0.08413699623909432, "media": 0.0, "plugin": 4.3527233157060775e-05, "reach": 0.006555630424481932, "reach_rank": 107, "referer_leaked": 0.695312804261087, "referer_leaked_header": 0.6324674977568202, "referer_leaked_url": 0.6394708004810905, "requests": 3.9684053378133286, "requests_failed": 1.2406525266795212, "requests_tracking": 2.394251732498425, "script": 0.9818079074473568, "site_reach": 0.0015278083339444564, "site_reach_rank": 342, "stylesheet": 3.932723697523911e-05, "tracked": 0.6156587312193352, "xhr": 0.0012504534086787194}, "date_range": ["2017-05", "2018-10"]}