{"id": "histats", "name": "Histats", "category": "advertising", "website_url": "http://www.histats.com/", "ghostery_id": "251", "company_id": "histats", "iab_vendor": null, "truste_type": "Attribution / Analytics", "description": "Website analytics company. ", "privacy_url": "http://www.histats.com/?act=5", "domains": ["histats.com"], "overview": {"bad_qs": 0.0, "beacon": 0.0, "content_length": 2024.2474891425766, "cookies": 0.38982143344147613, "font": 1.669730622358695e-06, "has_blocking": 0.336390053525998, "hosts": 1.0, "https": 0.6900601492627861, "iframe": 0.0, "image": 0.10054394257907703, "media": 0.0, "plugin": 0.0001335784497886956, "reach": 0.004497234308919422, "reach_rank": 150, "referer_leaked": 0.4189098106135871, "referer_leaked_header": 0.3951718069323876, "referer_leaked_url": 0.33404408200158403, "requests": 1.9015393246607524, "requests_failed": 1.0031552342993841, "requests_tracking": 0.5152070716431318, "script": 0.9128562022422256, "site_reach": 0.0065856872693009424, "site_reach_rank": 118, "stylesheet": 5.5657687411956495e-06, "tracked": 0.38982143344147613, "xhr": 0.00037123677503774985}, "date_range": ["2017-05", "2018-10"]}