{"id": "mirtesen.ru", "name": "mirtesen.ru", "category": "social_media", "website_url": "https://mirtesen.ru/", "ghostery_id": "mirtesen.ru", "company_id": null, "iab_vendor": null, "truste_type": null, "description": null, "privacy_url": null, "domains": ["mirtesen.ru"], "overview": {"bad_qs": 0.0, "beacon": 0.0, "content_length": 288.3279252749275, "cookies": 0.2308470988818847, "font": 9.202595131827175e-06, "has_blocking": 0.22893295909446465, "hosts": 1.0, "https": 0.6087700731606313, "iframe": 0.05717572355404224, "image": 0.004187180784981365, "media": 0.0, "plugin": 0.0, "reach": 0.00027199464694310115, "reach_rank": 829, "referer_leaked": 0.23964477982791146, "referer_leaked_header": 0.2395711590668569, "referer_leaked_url": 0.0034141627939078822, "requests": 3.488446141811991, "requests_failed": 1.4150462430405375, "requests_tracking": 1.7462108314544702, "script": 0.8823080108590623, "site_reach": 0.00021444873341911285, "site_reach_rank": 794, "stylesheet": 9.202595131827177e-05, "tracked": 0.2308470988818847, "xhr": 0.2686053467077716}, "date_range": ["2018-02", "2018-10"]}