{"id": "quisma", "name": "Quisma", "category": "advertising", "website_url": "http://www.quisma.com/en/", "ghostery_id": "537", "company_id": "quisma", "iab_vendor": null, "truste_type": null, "description": null, "privacy_url": "http://privacy.quisma.com/uk/privacy-policy/quisma-technologies/", "domains": ["qservz.com", "quisma.com"], "overview": {"bad_qs": 0.0, "beacon": 0.0, "content_length": 56.760560815731964, "cookies": 0.2606518572469046, "font": 0.0, "has_blocking": 0.4054989075018208, "hosts": 1.0001820830298616, "https": 1.000455207574654, "iframe": 0.0506190823015295, "image": 0.7022032046613256, "media": 0.0, "plugin": 0.0, "reach": 2.749357384643651e-05, "reach_rank": 1032, "referer_leaked": 0.3139111434814275, "referer_leaked_header": 0.3139111434814275, "referer_leaked_url": 0.0, "requests": 1.785688273852877, "requests_failed": 1.2797705753823745, "requests_tracking": 0.4817916970138383, "script": 0.3137290604515659, "site_reach": 4.444533335111146e-05, "site_reach_rank": 1016, "stylesheet": 9.104151493080844e-05, "tracked": 0.2606518572469046, "xhr": 0.0003641660597232338}, "date_range": ["2017-05", "2018-10"]}