{"id": "reevoo.com", "name": "Reevoo", "category": "site_analytics", "website_url": "https://www.reevoo.com/en/", "ghostery_id": "2222", "company_id": "reevoo", "iab_vendor": null, "truste_type": null, "description": null, "privacy_url": null, "domains": ["reevoo.com"], "overview": {"bad_qs": 0.1538778485626446, "beacon": 0.0, "content_length": 91151.70710120123, "cookies": 0.2816471744160248, "font": 0.045426452410383185, "has_blocking": 0.3976577604513328, "hosts": 1.0, "https": 1.5683338087540808, "iframe": 0.02114037589933758, "image": 0.4130217742702292, "media": 0.0, "plugin": 0.0, "reach": 0.00031589575689326964, "reach_rank": 805, "referer_leaked": 0.7946420081772368, "referer_leaked_header": 0.7870828182941904, "referer_leaked_url": 0.2252464264207157, "requests": 8.612579632975184, "requests_failed": 2.7730262115305377, "requests_tracking": 2.2994120630090964, "script": 0.9780910272257616, "site_reach": 0.0003100062001240025, "site_reach_rank": 698, "stylesheet": 0.7143989097017527, "tracked": 0.31616272067446355, "xhr": 0.0047542074736141495}, "date_range": ["2018-05", "2018-10"]}