{"id": "sentifi.com", "name": "Sentifi", "category": "site_analytics", "website_url": "https://sentifi.com/", "ghostery_id": null, "company_id": "sentifi", "iab_vendor": null, "truste_type": null, "description": null, "privacy_url": "https://sentifi.com/page/privacy/", "domains": ["sentifi.com"], "overview": {"bad_qs": 0.0, "beacon": 0.0, "content_length": 11022.107316316238, "cookies": 0.030366979595003486, "font": 0.20696718131740244, "has_blocking": 0.1857863294281946, "hosts": 1.0, "https": 1.5210955077973465, "iframe": 0.014011948172860578, "image": 0.5951121111024905, "media": 0.0, "plugin": 0.0, "reach": 0.00016130948347902412, "reach_rank": 920, "referer_leaked": 0.8996663821863604, "referer_leaked_header": 0.872821786019086, "referer_leaked_url": 0.5852897819846381, "requests": 13.37523469625262, "requests_failed": 2.7075801070680425, "requests_tracking": 0.20561719295523315, "script": 0.9917138645356506, "site_reach": 4.666760001866704e-05, "site_reach_rank": 1013, "stylesheet": 0.5908449065094267, "tracked": 0.030366979595003486, "xhr": 0.6738924664442548}, "date_range": ["2017-05", "2018-10"]}