{"id": "sharepoint", "name": "Microsoft SharePoint", "category": "customer_interaction", "website_url": "https://products.office.com/en-us/sharepoint/sharepoint-online-collaboration-software", "ghostery_id": null, "company_id": "microsoft", "iab_vendor": null, "truste_type": null, "description": null, "privacy_url": "https://privacy.microsoft.com/en-us/privacystatement/", "domains": ["sharepointonline.com"], "overview": {"bad_qs": 0.0, "beacon": 0.0, "content_length": 253036.50391032148, "cookies": 0.000553934338710778, "font": 0.4618313818520942, "has_blocking": 0.00023548899423453368, "hosts": 1.0, "https": 1.0394283504664956, "iframe": 0.0, "image": 0.05020732397532182, "media": 0.0, "plugin": 0.0, "reach": 0.0018707369551095746, "reach_rank": 310, "referer_leaked": 0.45020277475611503, "referer_leaked_header": 0.44959799620274, "referer_leaked_url": 0.014593627614295787, "requests": 11.543195505371425, "requests_failed": 4.041235996098377, "requests_tracking": 0.009233576984162026, "script": 0.4136872625876226, "site_reach": 0.00018778153340844598, "site_reach_rank": 830, "stylesheet": 0.14055615542808822, "tracked": 0.000553934338710778, "xhr": 0.08999024593881835}, "date_range": ["2018-03", "2018-10"]}