{"id": "smaato", "name": "Smaato", "category": "advertising", "website_url": "http://www.smaato.com/", "ghostery_id": "1647", "company_id": "spearhead", "iab_vendor": 82, "truste_type": null, "description": null, "privacy_url": null, "domains": ["smaato.net"], "overview": {"bad_qs": 0.0, "beacon": 0.0, "content_length": 76.59959591157596, "cookies": 0.00035654860946042314, "font": 0.0, "has_blocking": 0.28440694081293083, "hosts": 1.0, "https": 0.8838840028523889, "iframe": 0.0, "image": 0.8419895412407892, "media": 0.0, "plugin": 0.0, "reach": 4.2121436697727024e-05, "reach_rank": 1016, "referer_leaked": 0.05425481340622772, "referer_leaked_header": 0.05312574280960304, "referer_leaked_url": 0.003922034704064654, "requests": 1.9267886855241263, "requests_failed": 1.2721654385547896, "requests_tracking": 0.0005348229141906347, "script": 0.16009032564773001, "site_reach": 0.00018778153340844598, "site_reach_rank": 830, "stylesheet": 0.00035654860946042314, "tracked": 0.00035654860946042314, "xhr": 0.005407653910149751}, "date_range": ["2017-05", "2018-10"]}