{"id": "trafficforce", "name": "TrafficForce", "category": "advertising", "website_url": "http://www.trafficforce.com/", "ghostery_id": "2089", "company_id": "trafficforce", "iab_vendor": null, "truste_type": null, "description": null, "privacy_url": "http://www.trafficforce.com/terms.html", "domains": ["trafficforce.com"], "overview": {"bad_qs": 0.0, "beacon": 0.0, "content_length": 59552.650577765016, "cookies": 0.3411325629799756, "font": 0.0, "has_blocking": 0.6357568362879494, "hosts": 1.0, "https": 0.6866073351037106, "iframe": 0.2332232828536568, "image": 0.5553362520634465, "media": 0.0, "plugin": 0.0, "reach": 6.975017560131099e-05, "reach_rank": 993, "referer_leaked": 0.11009832771118926, "referer_leaked_header": 0.08074355845833632, "referer_leaked_url": 0.040264121151223714, "requests": 2.86786765233618, "requests_failed": 1.7712624703940285, "requests_tracking": 0.8355343429268642, "script": 0.4074140529677743, "site_reach": 0.00010555766670888975, "site_reach_rank": 920, "stylesheet": 0.0, "tracked": 0.3411325629799756, "xhr": 0.0}, "date_range": ["2017-06", "2018-10"]}