{"id": "trustarc", "name": "TrustArc", "category": "essential", "website_url": null, "ghostery_id": "c_775", "company_id": "trustarc", "iab_vendor": null, "truste_type": null, "description": null, "privacy_url": "https://www.trustarc.com/privacy-policy/", "domains": ["trustarc.com", "truste.com"], "overview": {"bad_qs": 0.0053515002758462, "beacon": 0.0, "content_length": 3019.800130323685, "cookies": 0.04194457716598048, "font": 0.005850290667161538, "has_blocking": 0.00118063853567233, "hosts": 1.0167833729818512, "https": 1.0758312543402742, "iframe": 0.03809952463764222, "image": 0.43172575597393853, "media": 0.0, "plugin": 0.0, "reach": 0.0029808425633483394, "reach_rank": 205, "referer_leaked": 0.8579186333479164, "referer_leaked_header": 0.8566254730741358, "referer_leaked_url": 0.03949513007596897, "requests": 3.5888094612308032, "requests_failed": 0.7921446391369079, "requests_tracking": 0.2958532380649284, "script": 0.9870154952509947, "site_reach": 0.001833370000733348, "site_reach_rank": 294, "stylesheet": 0.02233808415786296, "tracked": 0.04649498984365357, "xhr": 0.03218877452910912}, "date_range": ["2017-10", "2018-10"]}